eplan_parser/__init__.py
eplan_parser/get_keys.py
eplan_parser/input_gen.py
eplan_parser/output_parser.py
eplan_parser-0.7.dist-info/LICENSE
eplan_parser-0.7.dist-info/METADATA
eplan_parser-0.7.dist-info/WHEEL
eplan_parser-0.7.dist-info/entry_points.txt
eplan_parser-0.7.dist-info/top_level.txt
eplan_parser-0.7.dist-info/RECORD
