Metadata-Version: 2.1
Name: eplan_parser
Version: 0.7
Summary: Parser for the output files of EnergyPLAN
Author-email: Alex Sartori <alex.sartori1997@gmail.com>
Project-URL: Homepage, https://github.com/AlexSartori/eplan_parser
Classifier: Programming Language :: Python :: 3
Classifier: License :: OSI Approved :: MIT License
Classifier: Operating System :: OS Independent
Classifier: Development Status :: 4 - Beta
Classifier: Topic :: Utilities
Classifier: Topic :: Scientific/Engineering
Requires-Python: >=3.7
License-File: LICENSE
